twb/__init__.py
twb/bot.py
twb/manager.py
twb/cache/session.json
twb/core/__init__.py
twb/core/config.py
twb/core/exceptions.py
twb/core/extractors.py
twb/core/filemanager.py
twb/core/notification.py
twb/core/reporter.py
twb/core/request.py
twb/core/templates.py
twb/core/twstats.py
twb/core/updater.py
twb/core/utils.py
twb/game/__init__.py
twb/game/attack.py
twb/game/buildingmanager.py
twb/game/defence_manager.py
twb/game/hunter.py
twb/game/map.py
twb/game/reports.py
twb/game/resources.py
twb/game/simulator.py
twb/game/snobber.py
twb/game/troopmanager.py
twb/game/village.py
twb/pages/overview.py
twb/templates/config.example.json
twb/templates/builder/basic.txt
twb/templates/builder/purple_predator.txt
twb/templates/builder/purple_predator_into_def.txt
twb/templates/builder/purple_predator_into_off.txt
twb/templates/offensive/clear.txt
twb/templates/offensive/scout.txt
twb/templates/troops/basic.txt
twb/templates/troops/basic_into_def.txt
twb/templates/troops/basic_into_off.txt
twb/templates/troops/defensive.txt
twb/templates/troops/offensive.txt
twb/webmanager/__init__.py
twb/webmanager/helpfile.py
twb/webmanager/server.py
twb/webmanager/utils.py
twb/webmanager/static/images/announce.png
twb/webmanager/static/images/attack.png
twb/webmanager/static/images/attacked.png
twb/webmanager/static/images/back.png
twb/webmanager/static/images/cancel.png
twb/webmanager/static/images/favicon.png
twb/webmanager/static/images/favicon16.gif
twb/webmanager/static/images/favicon2.png
twb/webmanager/static/images/favicon32.gif
twb/webmanager/static/images/flag.png
twb/webmanager/static/images/flag_add.png
twb/webmanager/static/images/forum_active.png
twb/webmanager/static/images/forum_inactive.png
twb/webmanager/static/images/header.png
twb/webmanager/static/images/iron.png
twb/webmanager/static/images/message.png
twb/webmanager/static/images/palladin.png
twb/webmanager/static/images/return.png
twb/webmanager/static/images/stone.png
twb/webmanager/static/images/storage.png
twbot-2.0.2.dist-info/LICENSE.md
twbot-2.0.2.dist-info/WHEEL
twbot-2.0.2.dist-info/METADATA
twbot-2.0.2.dist-info/RECORD
