Metadata-Version: 2.1
Name: TWBot
Version: 2.0.2
Summary: Tribal Wars Bot
Author-email: matthewmoorcroft <matthewmoorcroft@gmail.com>
Requires-Python: >=3.8
Classifier: Programming Language :: Python :: 3
Classifier: License :: OSI Approved :: GNU General Public License v3 (GPLv3)
Classifier: Operating System :: OS Independent
Requires-Dist: requests>=2.32.3
Requires-Dist: beautifulsoup4>=4.12.3
Requires-Dist: lxml>=5.2.2
Requires-Dist: coloredlogs>=15.0.1
Requires-Dist: psutil>=5.9.8
Requires-Dist: flask>=2.2.5
Requires-Dist: pyquery>=2.0.0
Requires-Dist: python-telegram-bot>=21.3
Project-URL: Homepage, https://github.com/matthewmoorcroft/TWBot
Project-URL: Repository, https://github.com/matthewmoorcroft/TWBot
